fedzk/__init__.py
fedzk/__main__.py
fedzk/cli.py
fedzk/config_legacy.py
fedzk/artifacts/__init__.py
fedzk/artifacts/benchmarks/__init__.py
fedzk/artifacts/benchmarks/benchmark_results/__init__.py
fedzk/artifacts/proofs/__init__.py
fedzk/artifacts/tests/__init__.py
fedzk/artifacts/tests/test_results/__init__.py
fedzk/benchmark/__init__.py
fedzk/benchmark/benchmark_zk.py
fedzk/benchmark/cli.py
fedzk/benchmark/end_to_end.py
fedzk/benchmark/utils.py
fedzk/benchmark/visualization.py
fedzk/circuits/__init__.py
fedzk/cli/__init__.py
fedzk/client/__init__.py
fedzk/client/remote.py
fedzk/client/trainer.py
fedzk/compliance/__init__.py
fedzk/compliance/audit/__init__.py
fedzk/compliance/audit/audit_preparation.py
fedzk/compliance/audit/checklists.py
fedzk/compliance/audit/code_review.py
fedzk/compliance/audit/cryptographic_review.py
fedzk/compliance/audit/security_auditor.py
fedzk/compliance/privacy/__init__.py
fedzk/compliance/privacy/data_minimization.py
fedzk/compliance/privacy/privacy_assessor.py
fedzk/compliance/regulatory/__init__.py
fedzk/compliance/regulatory/compliance_reporting.py
fedzk/compliance/regulatory/industry_standards.py
fedzk/compliance/regulatory/privacy_compliance.py
fedzk/compliance/regulatory/regulatory_monitoring.py
fedzk/config/encryption.py
fedzk/config/environment.py
fedzk/config/hot_reload.py
fedzk/config/secrets_manager.py
fedzk/config/validator.py
fedzk/coordinator/__init__.py
fedzk/coordinator/aggregator.py
fedzk/coordinator/api.py
fedzk/coordinator/logic.py
fedzk/core/resource_optimizer.py
fedzk/core/scalability_manager.py
fedzk/logging/log_aggregation.py
fedzk/logging/security_compliance.py
fedzk/logging/structured_logger.py
fedzk/monitoring/__init__.py
fedzk/monitoring/metrics.py
fedzk/monitoring/metrics_server.py
fedzk/mpc/__init__.py
fedzk/mpc/client.py
fedzk/mpc/server.py
fedzk/prover/__init__.py
fedzk/prover/advanced_proof_validator.py
fedzk/prover/batch_zkgenerator.py
fedzk/prover/verifier.py
fedzk/prover/zk_key_manager.py
fedzk-1.1.0.dist-info/licenses/LICENSE
fedzk-1.1.0.dist-info/METADATA
fedzk-1.1.0.dist-info/WHEEL
fedzk-1.1.0.dist-info/entry_points.txt
fedzk-1.1.0.dist-info/top_level.txt
fedzk-1.1.0.dist-info/RECORD
