Metadata-Version: 2.4
Name: fedzk
Version: 1.1.0
Summary: Federated Learning with Zero-Knowledge Proofs
Home-page: https://github.com/fedzk/fedzk
Author: FEDZK Team
Author-email: support@fedzk.io
License: MIT
Project-URL: Homepage, https://fedzk.io
Project-URL: Documentation, https://docs.fedzk.io
Project-URL: Repository, https://github.com/fedzk/fedzk
Project-URL: Issues, https://github.com/fedzk/fedzk/issues
Project-URL: Changelog, https://github.com/fedzk/fedzk/blob/main/CHANGELOG.md
Platform: any
Classifier: Development Status :: 5 - Production/Stable
Classifier: Intended Audience :: Developers
Classifier: Intended Audience :: Financial and Insurance Industry
Classifier: Intended Audience :: Healthcare Industry
Classifier: Intended Audience :: Science/Research
Classifier: License :: OSI Approved :: MIT License
Classifier: Operating System :: OS Independent
Classifier: Programming Language :: Python :: 3
Classifier: Programming Language :: Python :: 3.8
Classifier: Programming Language :: Python :: 3.9
Classifier: Programming Language :: Python :: 3.10
Classifier: Programming Language :: Python :: 3.11
Classifier: Topic :: Scientific/Engineering :: Artificial Intelligence
Classifier: Topic :: Security :: Cryptography
Classifier: Topic :: Software Development :: Libraries :: Python Modules
Requires-Python: >=3.8
License-File: LICENSE
Requires-Dist: numpy>=1.21.0
Requires-Dist: pandas>=1.3.0
Requires-Dist: scikit-learn>=1.0.0
Requires-Dist: cryptography>=3.4.0
Requires-Dist: pydantic>=1.8.0
Requires-Dist: fastapi>=0.68.0
Requires-Dist: uvicorn>=0.15.0
Requires-Dist: requests>=2.25.0
Requires-Dist: aiofiles>=0.7.0
Requires-Dist: python-multipart>=0.0.5
Requires-Dist: python-jose[cryptography]>=3.3.0
Requires-Dist: passlib[bcrypt]>=1.7.0
Requires-Dist: sqlalchemy>=1.4.0
Requires-Dist: alembic>=1.7.0
Requires-Dist: redis>=4.0.0
Requires-Dist: celery>=5.2.0
Requires-Dist: prometheus-client>=0.12.0
Requires-Dist: opentelemetry-distro>=0.23b0
Requires-Dist: opentelemetry-instrumentation-fastapi>=0.23b0
Requires-Dist: structlog>=21.5.0
Requires-Dist: rich>=10.0.0
Requires-Dist: typer>=0.4.0
Requires-Dist: pymongo>=4.0.0
Provides-Extra: dev
Requires-Dist: pytest>=7.0.0; extra == "dev"
Requires-Dist: pytest-cov>=3.0.0; extra == "dev"
Requires-Dist: pytest-asyncio>=0.18.0; extra == "dev"
Requires-Dist: pytest-mock>=3.7.0; extra == "dev"
Requires-Dist: black>=22.0.0; extra == "dev"
Requires-Dist: isort>=5.10.0; extra == "dev"
Requires-Dist: flake8>=4.0.0; extra == "dev"
Requires-Dist: mypy>=0.950; extra == "dev"
Requires-Dist: pre-commit>=2.17.0; extra == "dev"
Requires-Dist: sphinx>=4.5.0; extra == "dev"
Requires-Dist: sphinx-rtd-theme>=1.0.0; extra == "dev"
Requires-Dist: sphinx-autodoc-typehints>=1.18.0; extra == "dev"
Requires-Dist: bandit>=1.7.0; extra == "dev"
Requires-Dist: safety>=2.0.0; extra == "dev"
Requires-Dist: coverage[toml]>=6.0.0; extra == "dev"
Provides-Extra: gpu
Requires-Dist: torch>=1.12.0; extra == "gpu"
Requires-Dist: torchvision>=0.13.0; extra == "gpu"
Requires-Dist: torchaudio>=0.12.0; extra == "gpu"
Requires-Dist: tensorflow>=2.9.0; extra == "gpu"
Requires-Dist: xgboost>=1.6.0; extra == "gpu"
Requires-Dist: lightgbm>=3.3.0; extra == "gpu"
Requires-Dist: catboost>=1.0.0; extra == "gpu"
Provides-Extra: docs
Requires-Dist: sphinx>=4.5.0; extra == "docs"
Requires-Dist: sphinx-rtd-theme>=1.0.0; extra == "docs"
Requires-Dist: sphinx-autodoc-typehints>=1.18.0; extra == "docs"
Requires-Dist: myst-parser>=0.17.0; extra == "docs"
Requires-Dist: sphinx-copybutton>=0.5.0; extra == "docs"
Requires-Dist: sphinx-design>=0.2.0; extra == "docs"
Dynamic: author
Dynamic: author-email
Dynamic: home-page
Dynamic: license-file
Dynamic: platform
Dynamic: requires-python
